{
	"message": "We could not find what you asked for, but got you this",
	"subject": "crk",
	"status": 200,
	"total": 120,
	"data": [
		{
			"id": 328,
			"question": "‘Blessed are you, Simon Bar-Jona ! For flesh and blood has not revealed this to you...’ As exemplified by the statement above, for believers to be able to identify with Jesus, they must",
			"option": {
				"a": "offer their lives",
				"b": "be led by the Spirit",
				"c": "keep all the commandments",
				"d": "vow not to deny Him."
			},
			"section": "",
			"image": "",
			"answer": "b",
			"solution": "",
			"examtype": "utme",
			"examyear": "2011"
		},
		{
			"id": 845,
			"question": "God made Pharaoh to chase and bring the Israelites back to Egypt so that He would",
			"option": {
				"a": "show that Moses was his true servant",
				"b": "destroy first born males of Egyptians",
				"c": "get glory over Pharaoh and his hosts",
				"d": "reveal his supernatural powers to the world"
			},
			"section": "",
			"image": "",
			"answer": "d",
			"solution": "",
			"examtype": "wassce",
			"examyear": "2012"
		},
		{
			"id": 1016,
			"question": "The incidents that took place following Jesus’ death on the cross did not include the ",
			"option": {
				"a": "tearing into two of the temple’s veil. ",
				"b": "quaking of the earth that broke the rocks. ",
				"c": "the opening of the tombs. ",
				"d": "trembling of the chief priest and his conversion"
			},
			"section": "",
			"image": "",
			"answer": "b",
			"solution": "",
			"examtype": "wassce",
			"examyear": "2011"
		},
		{
			"id": 202,
			"question": "When Saul and his troops came after David in the wilderness of Ziph, David and Abishai went to Saul’s camp \t\tto",
			"option": {
				"a": "slay him",
				"b": "surprise him",
				"c": "capture him alive",
				"d": "dialogue with him"
			},
			"section": "",
			"image": "",
			"answer": "b",
			"solution": "",
			"examtype": "wassce",
			"examyear": "2005"
		},
		{
			"id": 763,
			"question": "St Paul's teaching on spiritual gifts was directed to _______",
			"option": {
				"a": "Corinthians",
				"b": "Thessalonians",
				"c": "Galatians",
				"d": "Macedonians"
			},
			"section": "",
			"image": "",
			"answer": " a",
			"solution": "",
			"examtype": "utme",
			"examyear": "2019"
		},
		{
			"id": 722,
			"question": "The model example for wives in Christian families according to St Peter is _____",
			"option": {
				"a": "Ruth",
				"b": "Deborah",
				"c": "Sarah",
				"d": "Rebecca"
			},
			"section": "",
			"image": "",
			"answer": " c",
			"solution": "",
			"examtype": "utme",
			"examyear": "2019"
		},
		{
			"id": 85,
			"question": "Hosanna means  ",
			"option": {
				"a": "Ride on in majesty ",
				"b": "Ride on Glory ",
				"c": "Ride on to die ",
				"d": "Save me"
			},
			"section": "",
			"image": "",
			"answer": "d",
			"solution": "",
			"examtype": "post-utme",
			"examyear": "2009"
		},
		{
			"id": 464,
			"question": "Jeremiah said the people of Judah were in a state of mourning because,",
			"option": {
				"a": "they sinned against God.",
				"b": "their vessels were empty",
				"c": "their farms were destroyed.",
				"d": "there was drought in the land."
			},
			"section": "",
			"image": "",
			"answer": "a",
			"solution": "",
			"examtype": "wassce",
			"examyear": "2009"
		},
		{
			"id": 35,
			"question": "The prophet who was with the exiles of 597 BC in Babylon was ",
			"option": {
				"a": "Moses ",
				"b": "Hosea ",
				"c": "Micah ",
				"d": "Ezekiel."
			},
			"section": "",
			"image": "",
			"answer": "d",
			"solution": "",
			"examtype": "post-utme",
			"examyear": "2007"
		},
		{
			"id": 748,
			"question": "The Lord protected the Israelites with all but one of the following when the Egyptians chased them",
			"option": {
				"a": "Pillar of cloud",
				"b": "Pillar of darkness",
				"c": "Angels",
				"d": "Pillar of storm"
			},
			"section": "",
			"image": "",
			"answer": " d",
			"solution": "",
			"examtype": "utme",
			"examyear": "2019"
		},
		{
			"id": 1052,
			"question": "During the Ammonite war, Uriah disobeyed King David by refusing to go to his house to sleep because ",
			"option": {
				"a": "it was wrong to go home drunk",
				"b": "his wife would regard him as a coward ",
				"c": "it would be unpatriotic to break military vow ",
				"d": "he suspected that the king had lost interest in the battle"
			},
			"section": "",
			"image": "",
			"answer": "c",
			"solution": "",
			"examtype": "wassce",
			"examyear": "2015"
		},
		{
			"id": 378,
			"question": "Believers according to Jesus in John’s gospel, become his friends, if they imbibe his teaching on",
			"option": {
				"a": "forgiveness",
				"b": "obedience",
				"c": "love",
				"d": "faith."
			},
			"section": "",
			"image": "",
			"answer": "c",
			"solution": "",
			"examtype": "wassce",
			"examyear": "2008"
		},
		{
			"id": 8,
			"question": "What did God create on the fifth day? ",
			"option": {
				"a": "the firmament  ",
				"b": "the two great light ",
				"c": "water under the heaven ",
				"d": "living Creature"
			},
			"section": "",
			"image": "",
			"answer": "d",
			"solution": "",
			"examtype": "post-utme",
			"examyear": "2006"
		},
		{
			"id": 370,
			"question": "Which of the following miracles shows Jesus’ power over nature?",
			"option": {
				"a": "Walking on the sea",
				"b": "Healing of the leper",
				"c": "Healing of the woman with issue of blood",
				"d": "Raising of Lazarus from the dead"
			},
			"section": "",
			"image": "",
			"answer": "a",
			"solution": "",
			"examtype": "wassce",
			"examyear": "2008"
		},
		{
			"id": 745,
			"question": "St. Paul's teaching on forgiveness primarily shows that________",
			"option": {
				"a": "Subordinates must regard their superiors and vice-versa for forgiveness to thrive",
				"b": "Genuine forgiveness only comes from God",
				"c": "Christians must not institute a 'Master-Servant' relationship contract",
				"d": "Philemon had unilaterally decided not to accept Onesimus back"
			},
			"section": "",
			"image": "",
			"answer": " a",
			"solution": "",
			"examtype": "utme",
			"examyear": "2019"
		},
		{
			"id": 200,
			"question": "Moses was nursed by",
			"option": {
				"a": "Pharaoh’s daughter",
				"b": "Rachael",
				"c": "his mother",
				"d": "Rebecca"
			},
			"section": "",
			"image": "",
			"answer": "c",
			"solution": "",
			"examtype": "wassce",
			"examyear": "2005"
		},
		{
			"id": 799,
			"question": "When Abner wanted to transfer his allegiance to David, the latter gave him the condition ",
			"option": {
				"a": "openly submit to Joab",
				"b": "convince all Israel to come over to Davi  ",
				"c": "restore his wife Michal to him.    ",
				"d": "slay Ishbosheth. Saul’s successor."
			},
			"section": "",
			"image": "",
			"answer": "c",
			"solution": "",
			"examtype": "wassce",
			"examyear": "2010"
		},
		{
			"id": 596,
			"question": "What was God’s purpose in creating man?",
			"option": {
				"a": "To be master of all creation",
				"b": "To help Him look after the garden",
				"c": "To name the things He created",
				"d": "To multiply and fill the earth"
			},
			"section": "",
			"image": "",
			"answer": "d",
			"solution": "",
			"examtype": "utme",
			"examyear": "2010"
		},
		{
			"id": 186,
			"question": "What was the second temptation of Jesus according to the Gospel according to Luke?",
			"option": {
				"a": "The Devil wanted Jesus to worship him  ",
				"b": "The Devil wanted Jesus to deny God",
				"c": "The Devil wanted Jesus to jump from the pinnacle of the Temple    ",
				"d": "The devil wanted Jesus to turn stones to bread"
			},
			"section": "",
			"image": "",
			"answer": "a",
			"solution": "",
			"examtype": "post-utme",
			"examyear": "2013"
		},
		{
			"id": 693,
			"question": "The Galatians, were reminded by Paul that they were Abraham’s offspring and heirs according to",
			"option": {
				"a": "promise.",
				"b": "good works.",
				"c": "law.",
				"d": "grace."
			},
			"section": "",
			"image": "",
			"answer": "a",
			"solution": "",
			"examtype": "wassce",
			"examyear": "2011"
		},
		{
			"id": 856,
			"question": "The Hebrew kingdom broke up beacuse of ",
			"option": {
				"a": "prophet Ahijah’s curse against solomon",
				"b": "Solomon’s marriage to foreign women",
				"c": "Rehoboam’s efforts to rule Shechem",
				"d": "Rehoboam’s refusal to grant the Northerners’ petition"
			},
			"section": "",
			"image": "",
			"answer": "d",
			"solution": "",
			"examtype": "wassce",
			"examyear": "2012"
		},
		{
			"id": 166,
			"question": "Eli’s inability to discipline his sons led to all the following except  ",
			"option": {
				"a": "God’s curse on his family  ",
				"b": "the extension of his life span  ",
				"c": "the cancellation of priesthood from his lineage",
				"d": "the death of his sons"
			},
			"section": "",
			"image": "",
			"answer": "b",
			"solution": "",
			"examtype": "post-utme",
			"examyear": "2012"
		},
		{
			"id": 155,
			"question": "The disciple in Damascus who prayed for Saul (Paul) to receive his sight after his conversions was  ",
			"option": {
				"a": "Ananias ",
				"b": "Sapphira  ",
				"c": "Barnabas  ",
				"d": "Thomas "
			},
			"section": "",
			"image": "",
			"answer": "a",
			"solution": "",
			"examtype": "post-utme",
			"examyear": "2012"
		},
		{
			"id": 235,
			"question": "Paul said he was not fit to be called an apostle because he",
			"option": {
				"a": "was not called like the others",
				"b": "was not a Jew",
				"c": "persecuted the Early Church",
				"d": "was only a distributor of letters"
			},
			"section": "",
			"image": "",
			"answer": "c",
			"solution": "",
			"examtype": "wassce",
			"examyear": "2005"
		},
		{
			"id": 913,
			"question": "Jesus demonstrated his compassion for humanity in all the following miracles except the ",
			"option": {
				"a": "feeding of the five thousan",
				"b": "healing of the centurion’s servant. ",
				"c": "feeding of the four thousand.",
				"d": "healing of the paralytic."
			},
			"section": "",
			"image": "",
			"answer": "b",
			"solution": "",
			"examtype": "wassce",
			"examyear": "2013"
		},
		{
			"id": 930,
			"question": "Paul’s letter to Philemon emphasizes",
			"option": {
				"a": "humility.         love.          forgiveness.     sincerity",
				"b": "",
				"c": "",
				"d": ""
			},
			"section": "",
			"image": "",
			"answer": "c",
			"solution": "",
			"examtype": "wassce",
			"examyear": "2013"
		},
		{
			"id": 962,
			"question": "All the following took place at the transfiguration of Jesus except that",
			"option": {
				"a": "a voice was heard from heaven.",
				"b": "a dove came down upon Jesus",
				"c": "the face of Jesus was changed",
				"d": "Jesus’ clothes became dazzling white."
			},
			"section": "",
			"image": "",
			"answer": "b",
			"solution": "",
			"examtype": "wassce",
			"examyear": "2011"
		},
		{
			"id": 10,
			"question": "Manahem, the son of Gadi reigned over Israel for ",
			"option": {
				"a": "eight years ",
				"b": "twenty years ",
				"c": "six month ",
				"d": "ten years."
			},
			"section": "",
			"image": "",
			"answer": "d",
			"solution": "",
			"examtype": "post-utme",
			"examyear": "2006"
		},
		{
			"id": 436,
			"question": "According to Galatians, judgment is without mercy to one who has shown no mercy, yet mercy triumphs over",
			"option": {
				"a": "tribulation",
				"b": "the law",
				"c": "judgment",
				"d": "punishment."
			},
			"section": "",
			"image": "",
			"answer": "a",
			"solution": "",
			"examtype": "utme",
			"examyear": "2013"
		},
		{
			"id": 624,
			"question": "After the healing of the demoniac in the country of the Gerasenes, the people begged Jesus to (Mark 5:15-19)",
			"option": {
				"a": "stay with them",
				"b": "visit them always",
				"c": "go away from them",
				"d": "heal their sick."
			},
			"section": "",
			"image": "",
			"answer": "c",
			"solution": "",
			"examtype": "utme",
			"examyear": "2010"
		},
		{
			"id": 579,
			"question": "The conversion of the Ethiopian eunuch confirms the",
			"option": {
				"a": "universality of the gospel.",
				"b": "work of the Apostles.",
				"c": "work of Philip in Samaria",
				"d": "the love of God for the eunuch."
			},
			"section": "",
			"image": "",
			"answer": "a",
			"solution": "",
			"examtype": "wassce",
			"examyear": "2010"
		},
		{
			"id": 73,
			"question": "Joshua’s first victory was over the people of ",
			"option": {
				"a": "Ai ",
				"b": "Gideon ",
				"c": "Gilgal ",
				"d": "Jericho "
			},
			"section": "",
			"image": "",
			"answer": "d",
			"solution": "",
			"examtype": "post-utme",
			"examyear": "2008"
		},
		{
			"id": 55,
			"question": "The lesson, who Jesus teaches in the parable of the Good Samaritan is that your neighbor is ",
			"option": {
				"a": "only your friend ",
				"b": "your next of king ",
				"c": "a distant friend ",
				"d": "anyone who needs your help"
			},
			"section": "",
			"image": "",
			"answer": "d",
			"solution": "",
			"examtype": "post-utme",
			"examyear": "2008"
		},
		{
			"id": 736,
			"question": "One of the following is not a condition for effective prayer according to St James_____",
			"option": {
				"a": "Faith",
				"b": "Lowliness",
				"c": "Steadfastness",
				"d": "Perseverance"
			},
			"section": "",
			"image": "",
			"answer": " b",
			"solution": "",
			"examtype": "utme",
			"examyear": "2019"
		},
		{
			"id": 511,
			"question": "A good example of parental responsibility was demonstrated by",
			"option": {
				"a": "Samuel",
				"b": "Eli",
				"c": "Asa",
				"d": "David"
			},
			"section": "",
			"image": "",
			"answer": "c",
			"solution": "",
			"examtype": "utme",
			"examyear": "2015"
		},
		{
			"id": 241,
			"question": "At the coming of the Lord, unbelievers will",
			"option": {
				"a": "be condemned",
				"b": "have a desolate land",
				"c": "be hit by famine",
				"d": "die in divine war"
			},
			"section": "",
			"image": "",
			"answer": "a",
			"solution": "",
			"examtype": "wassce",
			"examyear": "2005"
		},
		{
			"id": 109,
			"question": "That was the sin of David that involved Bathseba? ",
			"option": {
				"a": "Murder ",
				"b": "adultery ",
				"c": "dishonesty ",
				"d": "arrogance"
			},
			"section": "",
			"image": "",
			"answer": "a",
			"solution": "",
			"examtype": "post-utme",
			"examyear": "2010"
		},
		{
			"id": 692,
			"question": "James strongly condemned partiality in the Church for all the following reasons except that it",
			"option": {
				"a": "is contrary to Christ’s example of humility",
				"b": "accords due respect to the rich who merit it.",
				"c": "is a transgression of the commandment of God.",
				"d": "does not harmonize with the Christian virtue of love."
			},
			"section": "",
			"image": "",
			"answer": "d",
			"solution": "",
			"examtype": "wassce",
			"examyear": "2011"
		},
		{
			"id": 825,
			"question": "After his conversion, Paul was introduced to the disciples in Jerusalem by ",
			"option": {
				"a": " Peter           ",
				"b": "  Ananias",
				"c": "Barnabas",
				"d": "Philip"
			},
			"section": "",
			"image": "",
			"answer": "c",
			"solution": "",
			"examtype": "wassce",
			"examyear": "2010"
		},
		{
			"id": 148,
			"question": "In his second letter to the Christians in Thessalonians, Paul admonished them to have nothing to do with anyone who refused to obey what he wrote in the letter. What did Paul think would happen to the person?  ",
			"option": {
				"a": "The person would be encouraged  ",
				"b": "The person would be ashamed  ",
				"c": "The person would be disturbed  ",
				"d": "The person would repent"
			},
			"section": "",
			"image": "",
			"answer": "b",
			"solution": "",
			"examtype": "post-utme",
			"examyear": "2012"
		},
		{
			"id": 196,
			"question": "The eunuch who went to Jerusalem to worship in Acts 8:27 was a  ",
			"option": {
				"a": "minister of God  ",
				"b": "minister of Candace the queen Gaza  ",
				"c": "minister of Candace the king of the Ethiopians",
				"d": "minister of Candace the queen of the Ethiopians"
			},
			"section": "",
			"image": "",
			"answer": "d",
			"solution": "",
			"examtype": "post-utme",
			"examyear": "2013"
		},
		{
			"id": 408,
			"question": "Saul relied on a medium because God did not answer him through",
			"option": {
				"a": "dreams, visions and prophets",
				"b": "inspiration, tambourines and prophets",
				"c": "dreams, urim and prophets",
				"d": "lyre, urim and prophets."
			},
			"section": "",
			"image": "",
			"answer": "c",
			"solution": "",
			"examtype": "utme",
			"examyear": "2013"
		},
		{
			"id": 523,
			"question": "“How is it that you have agreed together to tempt the spirit of the Lord ....” The statement above was made in reference to the greed of",
			"option": {
				"a": "Gehazi and Naaman",
				"b": "Ahab and Jezebel",
				"c": "Judas and scribes",
				"d": "Ananias and Sapphira"
			},
			"section": "",
			"image": "",
			"answer": "d",
			"solution": "",
			"examtype": "utme",
			"examyear": "2015"
		},
		{
			"id": 823,
			"question": "When the apostles in Jerusalem heard that Samaria had received the gospel, they sent to them   ",
			"option": {
				"a": "Mark and Barnabas. ",
				"b": "Peter and John. ",
				"c": "Paul and John. ",
				"d": "Peter and Paul."
			},
			"section": "",
			"image": "",
			"answer": "b",
			"solution": "",
			"examtype": "wassce",
			"examyear": "2010"
		},
		{
			"id": 648,
			"question": "“…who is the Lord that I should heed his voice and let Israel go”? After this statement, Pharaoh",
			"option": {
				"a": "engaged Israel into forced labour with task masters.",
				"b": "ordered midwives to kill all males born to Israelites.",
				"c": "asked Israelites to fetch their own straws to produce bricks.",
				"d": "decreed that Israelites’ male babies be drowned in the Nile."
			},
			"section": "",
			"image": "",
			"answer": "c",
			"solution": "",
			"examtype": "wassce",
			"examyear": "2011"
		},
		{
			"id": 671,
			"question": "The incidents that took place following Jesus’ death on the cross did not include the",
			"option": {
				"a": "tearing into two of the temple’s veil.",
				"b": "quaking of the earth that broke the rocks.",
				"c": "the opening of the tombs.",
				"d": "trembling of the chief priest and his conversion."
			},
			"section": "",
			"image": "",
			"answer": "b",
			"solution": "",
			"examtype": "wassce",
			"examyear": "2011"
		},
		{
			"id": 702,
			"question": "Praying for others is a prayer of _____________.",
			"option": {
				"a": "apprehension",
				"b": "interceding",
				"c": "intercession",
				"d": "appreciation"
			},
			"section": "",
			"image": "",
			"answer": " c",
			"solution": "",
			"examtype": "utme",
			"examyear": "2019"
		},
		{
			"id": 621,
			"question": "Jesus was tempted by the devil so as to",
			"option": {
				"a": "fulfil all righteousness",
				"b": "show His power over forces of nature",
				"c": "show that no one is above temptation",
				"d": "test the devil’s power"
			},
			"section": "",
			"image": "",
			"answer": "c",
			"solution": "",
			"examtype": "utme",
			"examyear": "2010"
		},
		{
			"id": 881,
			"question": "And we are witnesses to these  things, and so is the Holy Spirit whom God has given to those who obey him”\n “These things” in the disciples’ statement before the\n Sanhedrin refers to\n",
			"option": {
				"a": "the election of Matthias",
				"b": "outpouring of the Holy Spirit",
				"c": "cater for the poor and needy",
				"d": "defend Christianity as a true religious "
			},
			"section": "",
			"image": "",
			"answer": "d",
			"solution": "",
			"examtype": "wassce",
			"examyear": "2012"
		},
		{
			"id": 358,
			"question": "A good example of parental responsibility was demonstrated by",
			"option": {
				"a": "Asa",
				"b": "Jeroboam",
				"c": "Joel",
				"d": "Rehoboam."
			},
			"section": "",
			"image": "",
			"answer": "a",
			"solution": "",
			"examtype": "wassce",
			"examyear": "2008"
		},
		{
			"id": 809,
			"question": "According to Amos’ prophecy, the “Day of the Lord” to the Israelites would be a day of ",
			"option": {
				"a": "victory over enemies    ",
				"b": " happiness",
				"c": "doom",
				"d": "national triumph"
			},
			"section": "",
			"image": "",
			"answer": "c",
			"solution": "",
			"examtype": "wassce",
			"examyear": "2010"
		},
		{
			"id": 140,
			"question": "Among the spiritual gifts, love is supreme because it ",
			"option": {
				"a": "facilitates development ",
				"b": "gives room for friendship ",
				"c": "has eternal value ",
				"d": "promotes understanding"
			},
			"section": "",
			"image": "",
			"answer": "c",
			"solution": "",
			"examtype": "post-utme",
			"examyear": "2011"
		},
		{
			"id": 294,
			"question": "According to Prophet Jeremiah, one of the promises of God was that He would give the Israelites",
			"option": {
				"a": "new priests",
				"b": "new commandments",
				"c": "kings after His own heart",
				"d": "shepherds after His own heart."
			},
			"section": "",
			"image": "",
			"answer": "c",
			"solution": "",
			"examtype": "utme",
			"examyear": "2009"
		},
		{
			"id": 896,
			"question": "Moses ran away from Egypt because he ",
			"option": {
				"a": "did not like to be trained in Egypt. ",
				"b": "could no longer bear the hunger in the lan",
				"c": "feared the news of his murder would reach the king. ",
				"d": "heard a divine call to save his people."
			},
			"section": "",
			"image": "",
			"answer": "c",
			"solution": "",
			"examtype": "wassce",
			"examyear": "2013"
		},
		{
			"id": 800,
			"question": "slay Ishbosheth. Saul’s successor.",
			"option": {
				"a": "Power and authority ",
				"b": "Great wealth and riches ",
				"c": "Stable and long term in office ",
				"d": "An understanding mind"
			},
			"section": "",
			"image": "",
			"answer": "d",
			"solution": "",
			"examtype": "wassce",
			"examyear": "2010"
		},
		{
			"id": 984,
			"question": "Paul believes that the resurrection of the dead would only occur on the",
			"option": {
				"a": "last day.",
				"b": "triumphant day.",
				"c": "ascension day",
				"d": "pentecost day."
			},
			"section": "",
			"image": "",
			"answer": "a",
			"solution": "",
			"examtype": "wassce",
			"examyear": "2011"
		},
		{
			"id": 90,
			"question": "The seven deacons were appointed by ",
			"option": {
				"a": "conduct a mission to the Gentiles",
				"b": "Replace the twelve ",
				"c": "Lead the church in Jerusalem ",
				"d": "Help in the distribution of food "
			},
			"section": "",
			"image": "",
			"answer": "d",
			"solution": "",
			"examtype": "post-utme",
			"examyear": "2009"
		},
		{
			"id": 1080,
			"question": "Peter’s tour of Lydda led to the",
			"option": {
				"a": "development of the church in Caesarca ",
				"b": "conversion of the residents of sharon ",
				"c": "conversion of Cornelius and his household ",
				"d": "healing of Dorcas and her family"
			},
			"section": "",
			"image": "",
			"answer": "b",
			"solution": "",
			"examtype": "wassce",
			"examyear": "2015"
		},
		{
			"id": 92,
			"question": "Joshua’s first victory was in ",
			"option": {
				"a": "Ai ",
				"b": "Gibeon ",
				"c": "Jordan ",
				"d": "Giligal "
			},
			"section": "",
			"image": "",
			"answer": "c",
			"solution": "",
			"examtype": "post-utme",
			"examyear": "2009"
		},
		{
			"id": 31,
			"question": "Israel went into Assyrain captivity in ",
			"option": {
				"a": "71AD ",
				"b": "720BC ",
				"c": "722BC ",
				"d": "68AD"
			},
			"section": "",
			"image": "",
			"answer": "c",
			"solution": "",
			"examtype": "post-utme",
			"examyear": "2007"
		},
		{
			"id": 1029,
			"question": "Which of the following is not true about spiritual gifts as taught by Paul? ",
			"option": {
				"a": "Gifts should be used with all modesty ",
				"b": "No gift can be independent of others ",
				"c": "Gifts have nothing to do with the level of one’s faith ",
				"d": "Specific gifts perform specific functions"
			},
			"section": "",
			"image": "",
			"answer": "b",
			"solution": "",
			"examtype": "wassce",
			"examyear": "2011"
		},
		{
			"id": 174,
			"question": "Israel went into Assyria captivity in",
			"option": {
				"a": "720BC  ",
				"b": "730 AD   ",
				"c": "750BC",
				"d": "722 BC"
			},
			"section": "",
			"image": "",
			"answer": "d",
			"solution": "",
			"examtype": "post-utme",
			"examyear": "2013"
		},
		{
			"id": 544,
			"question": "God’s message through Jonah’s was to the people of",
			"option": {
				"a": "Joppa",
				"b": "Tarshish",
				"c": "Samaira",
				"d": "Nineveh"
			},
			"section": "",
			"image": "",
			"answer": "d",
			"solution": "",
			"examtype": "utme",
			"examyear": "2015"
		},
		{
			"id": 107,
			"question": "When was this statement made? ‘I repent that I Made Saul king '",
			"option": {
				"a": "at the anointing of Saul ",
				"b": "When Saul failed to ray ",
				"c": "When Saul disobeyed God over Amalek ",
				"d": "When Saul finished the morning offering"
			},
			"section": "",
			"image": "",
			"answer": "c",
			"solution": "",
			"examtype": "post-utme",
			"examyear": "2010"
		},
		{
			"id": 484,
			"question": "Paul and his associates gave the Thessalonian believers an \timportant example to imitate. This example was to",
			"option": {
				"a": "be ready to help the poor always",
				"b": "toil, labour and work to earn a living",
				"c": "depend on foreign aids for sustenance.",
				"d": "suffer imprisonment without complaint."
			},
			"section": "",
			"image": "",
			"answer": "b",
			"solution": "",
			"examtype": "wassce",
			"examyear": "2009"
		},
		{
			"id": 4,
			"question": "The thief as described by Jesus comes to ",
			"option": {
				"a": "destroy, kill and steal ",
				"b": "destroy, steal and kill ",
				"c": "kill, destroy and kill ",
				"d": "steal, kill and destroy "
			},
			"section": "",
			"image": "",
			"answer": "d",
			"solution": "",
			"examtype": "post-utme",
			"examyear": "2006"
		},
		{
			"id": 664,
			"question": "King Jehoshaphat was commended for adopting his father’s policies which included",
			"option": {
				"a": "removing Maacah, his grandmother from being queen.",
				"b": "waging wars with the king of Israel.",
				"c": "allowing the cult prostitutes to operate.",
				"d": "burning of incense at the high places."
			},
			"section": "",
			"image": "",
			"answer": "a",
			"solution": "",
			"examtype": "wassce",
			"examyear": "2011"
		},
		{
			"id": 499,
			"question": "According to Amos, true religion entails",
			"option": {
				"a": "engaging in sacrifices and burnt offerings",
				"b": "being just and righteous",
				"c": "fasting and praying always",
				"d": "engaging in holy feasts and assemblies"
			},
			"section": "",
			"image": "",
			"answer": "b",
			"solution": "",
			"examtype": "utme",
			"examyear": "2015"
		},
		{
			"id": 533,
			"question": "“Holy, holy, holy is the Lord of host ....” The statement above was made in reference to the call of",
			"option": {
				"a": "Ezekiel",
				"b": "Jeremiah",
				"c": "Amos",
				"d": "Isaiah"
			},
			"section": "",
			"image": "",
			"answer": "d",
			"solution": "",
			"examtype": "utme",
			"examyear": "2015"
		},
		{
			"id": 260,
			"question": "According to Luke, when Moses and Elijah appeared during the Transfiguration, they spoke of Jesus’",
			"option": {
				"a": "departure",
				"b": "second coming",
				"c": "resurrection",
				"d": "trials."
			},
			"section": "",
			"image": "",
			"answer": "a",
			"solution": "",
			"examtype": "utme",
			"examyear": "2009"
		},
		{
			"id": 130,
			"question": "What was Cain’s immediate reaction to the acceptance of Abel’s offering?",
			"option": {
				"a": "He offered another sacrifice ",
				"b": "He was angry and his countenance fell ",
				"c": "He was angry with God",
				"d": "He was angry with Abel "
			},
			"section": "",
			"image": "",
			"answer": "b",
			"solution": "",
			"examtype": "post-utme",
			"examyear": "2011"
		},
		{
			"id": 788,
			"question": "To St. James, a doer of the word of God must learn to also__________",
			"option": {
				"a": "persevere in times of tribulation",
				"b": "combine his faith with work",
				"c": "be a listener of the word of God",
				"d": "control his tongue"
			},
			"section": "",
			"image": "",
			"answer": " d",
			"solution": "",
			"examtype": "utme",
			"examyear": "2019"
		},
		{
			"id": 682,
			"question": "According to Paul, ‘As sin reigned in death, grace also might reign through righteousness to",
			"option": {
				"a": "faith in God’.",
				"b": "the knowledge of God’.",
				"c": "eternal life",
				"d": "the glory of the father’."
			},
			"section": "",
			"image": "",
			"answer": "c",
			"solution": "",
			"examtype": "wassce",
			"examyear": "2011"
		},
		{
			"id": 1012,
			"question": " “And I asked them concerning the Jews that survived, who has escaped exile, and concerning Jerusalem...” These were   the words of ",
			"option": {
				"a": "Jeremiah. ",
				"b": "  Nehemiah ",
				"c": " Ezr",
				"d": "Hanani"
			},
			"section": "",
			"image": "",
			"answer": "b",
			"solution": "",
			"examtype": "wassce",
			"examyear": "2011"
		},
		{
			"id": 420,
			"question": "According to Jeremiah, the people of Israel were in exile because of their",
			"option": {
				"a": "impatience and immorality",
				"b": "rebellion against Nebuchadnezzar",
				"c": "maltreatment of the poor",
				"d": "unfaithfulness and faithlessness."
			},
			"section": "",
			"image": "",
			"answer": "b",
			"solution": "",
			"examtype": "utme",
			"examyear": "2013"
		},
		{
			"id": 65,
			"question": "The meaning of Emmanuel is ",
			"option": {
				"a": "laughter ",
				"b": "for I draw him from water ",
				"c": "God with us ",
				"d": "the fear of God"
			},
			"section": "",
			"image": "",
			"answer": "c",
			"solution": "",
			"examtype": "post-utme",
			"examyear": "2008"
		},
		{
			"id": 729,
			"question": "St. Peter's teaching on Civic Responsibility centers upon_____",
			"option": {
				"a": "Good Neighbourliness",
				"b": "Social Advancement",
				"c": "Good Citizenship",
				"d": "Social Justice"
			},
			"section": "",
			"image": "",
			"answer": " c",
			"solution": "",
			"examtype": "utme",
			"examyear": "2019"
		},
		{
			"id": 87,
			"question": "Let his habitation be made desolate, and let there be no one to live in it’ who is being referred to here?  ",
			"option": {
				"a": "King soul ",
				"b": "Judas Iscariot ",
				"c": "Stephen ",
				"d": "Barnabas "
			},
			"section": "",
			"image": "",
			"answer": "b",
			"solution": "",
			"examtype": "post-utme",
			"examyear": "2009"
		},
		{
			"id": 100,
			"question": "Deborah was a judge when Israel was under the yoke of ",
			"option": {
				"a": "Moab ",
				"b": "Midian ",
				"c": "Canaan ",
				"d": "Philistine"
			},
			"section": "",
			"image": "",
			"answer": "c",
			"solution": "",
			"examtype": "post-utme",
			"examyear": "2010"
		},
		{
			"id": 1005,
			"question": "In spite of Solomon’s apostasy, his empire remained intact until his death because ",
			"option": {
				"a": "God deferred, for David’s sake, the punishment due to him",
				"b": " he won decisive victories over his enemies. ",
				"c": "he always took wise decisions",
				"d": "he made surrounding nations fight among themselves."
			},
			"section": "",
			"image": "",
			"answer": "a",
			"solution": "",
			"examtype": "wassce",
			"examyear": "2011"
		},
		{
			"id": 314,
			"question": "Nehemiah responded to the opposition of the enemies of Israel by",
			"option": {
				"a": "telling the people not to say a word",
				"b": "reporting the issue to King Artaxerxes",
				"c": "inviting them to dialogue in the King’s court",
				"d": "asking God to return their taunt back to them."
			},
			"section": "",
			"image": "",
			"answer": "d",
			"solution": "",
			"examtype": "utme",
			"examyear": "2011"
		},
		{
			"id": 689,
			"question": "Paul asked the Thessalonians to imitate his action of",
			"option": {
				"a": "demanding support from his converts.",
				"b": "performing miracles",
				"c": "healing the sick.",
				"d": "working for his personal upkeep."
			},
			"section": "",
			"image": "",
			"answer": "d",
			"solution": "",
			"examtype": "wassce",
			"examyear": "2011"
		},
		{
			"id": 531,
			"question": "A key requirement for healing as exemplified by the disciple’s inability to heal the epileptic boy is",
			"option": {
				"a": "righteousness",
				"b": "power",
				"c": "humility",
				"d": "Faith"
			},
			"section": "",
			"image": "",
			"answer": "b",
			"solution": "",
			"examtype": "utme",
			"examyear": "2015"
		},
		{
			"id": 928,
			"question": "Luke described Cornelius as a devout man who feared God because he was a ",
			"option": {
				"a": "Hellenist of the Italian Cohort. ",
				"b": "Proselyte of Jewish descent. ",
				"c": "Greek who favoured Jewish religion. ",
				"d": "Proselyte in sympathy with Jewish faith."
			},
			"section": "",
			"image": "",
			"answer": "c",
			"solution": "",
			"examtype": "wassce",
			"examyear": "2013"
		},
		{
			"id": 1058,
			"question": "Which of the following events could be attributed to Josiah? ",
			"option": {
				"a": "Establishing relationship with Assyria ",
				"b": "Reconstruction of the valley of Hinnon ",
				"c": "Revival of the feast of the Passover ",
				"d": "Building walls around Jerusalem"
			},
			"section": "      ",
			"image": "",
			"answer": "c",
			"solution": "",
			"examtype": "wassce",
			"examyear": "2015"
		},
		{
			"id": 909,
			"question": "God addressed Ezekiel as the “Son of man “. This phrase ",
			"option": {
				"a": "humanity.      ",
				"b": "character",
				"c": "C.. humility",
				"d": "elegance"
			},
			"section": "",
			"image": "",
			"answer": "a",
			"solution": "",
			"examtype": "wassce",
			"examyear": "2013"
		},
		{
			"id": 226,
			"question": "Before his ascension, Jesus commissioned his disciples to go to all nations and",
			"option": {
				"a": "cast out demons",
				"b": "heal the sick",
				"c": "raise the dead",
				"d": "make disciples of them"
			},
			"section": "",
			"image": "",
			"answer": "d",
			"solution": "",
			"examtype": "wassce",
			"examyear": "2005"
		},
		{
			"id": 967,
			"question": "The initial evidence that the disciples had received the Holy Spirit was",
			"option": {
				"a": "performing miracles",
				"b": "preaching to the people. ",
				"c": "speaking in tongues. ",
				"d": "praying together"
			},
			"section": "",
			"image": "",
			"answer": "c",
			"solution": "",
			"examtype": "wassce",
			"examyear": "2011"
		},
		{
			"id": 727,
			"question": "A Christian can demonstrate that he is light of the world by___________",
			"option": {
				"a": "Advocating for the meek to inherit the earth",
				"b": "being committed to improving himself",
				"c": "being merciful to persons in need",
				"d": "Upholding good moral values"
			},
			"section": "",
			"image": "",
			"answer": " d",
			"solution": "",
			"examtype": "utme",
			"examyear": "2019"
		},
		{
			"id": 1064,
			"question": "“I gave you cleanness of teeth in all your cities” This statement means God gave them",
			"option": {
				"a": "no water to drink ",
				"b": "new set of teeth ",
				"c": "no food to eat                       ",
				"d": "no teeth at all"
			},
			"section": "",
			"image": "",
			"answer": "b",
			"solution": "",
			"examtype": "wassce",
			"examyear": "2015"
		},
		{
			"id": 164,
			"question": "The person who was invited to nurse Moses was ",
			"option": {
				"a": "Jochebed  ",
				"b": "Puah  ",
				"c": "Shiphrah  ",
				"d": "Miriam "
			},
			"section": "",
			"image": "",
			"answer": "a",
			"solution": "",
			"examtype": "post-utme",
			"examyear": "2012"
		},
		{
			"id": 846,
			"question": "The minority report of the twelve spies was presented by",
			"option": {
				"a": "Caleb and Joshua",
				"b": "Palti and Gaddiel",
				"c": "Joshua and Ammiel",
				"d": "Sethur and Gaddiel"
			},
			"section": "",
			"image": "",
			"answer": "a",
			"solution": "",
			"examtype": "wassce",
			"examyear": "2012"
		},
		{
			"id": 50,
			"question": "Daniel was delivered from the den of lion for all the following reason except ",
			"option": {
				"a": "his holiness and faith ",
				"b": "his kindness ",
				"c": "God’s love for him ",
				"d": "God’s mighty power."
			},
			"section": "",
			"image": "",
			"answer": "b",
			"solution": "",
			"examtype": "post-utme",
			"examyear": "2008"
		},
		{
			"id": 144,
			"question": "What did Ahab do to Prophet Micaiah for speaking the truth about the war between Israel and Syria? ",
			"option": {
				"a": "he promoted him ",
				"b": "he gave him a gift ",
				"c": "he denied him any fox ",
				"d": "he imprisoned him."
			},
			"section": "",
			"image": "",
			"answer": "d",
			"solution": "",
			"examtype": "post-utme",
			"examyear": "2011"
		},
		{
			"id": 609,
			"question": "Naaman’s leprosy was transferred to Gehazi be¬cause Gehazi was",
			"option": {
				"a": "ambitious",
				"b": "anxious",
				"c": "covetous",
				"d": "contemptuous"
			},
			"section": "",
			"image": "",
			"answer": "c",
			"solution": "",
			"examtype": "utme",
			"examyear": "2010"
		},
		{
			"id": 710,
			"question": "Which of these is not in the list of the twelve apostles?",
			"option": {
				"a": "Thaddeus",
				"b": "Matthew",
				"c": "Mark",
				"d": "Simon the Zealot"
			},
			"section": "",
			"image": "",
			"answer": " c",
			"solution": "",
			"examtype": "utme",
			"examyear": "2019"
		},
		{
			"id": 982,
			"question": "James teaches that all the following are true causes of unanswered prayers except ",
			"option": {
				"a": "sin",
				"b": "diligence",
				"c": "unfaithfulness",
				"d": "greed"
			},
			"section": "",
			"image": "",
			"answer": "b",
			"solution": "",
			"examtype": "wassce",
			"examyear": "2011"
		},
		{
			"id": 918,
			"question": "“He saved others, he cannot save himself. This was said by the",
			"option": {
				"a": "Scribes and elders.",
				"b": "        Roman authority.",
				"c": "Crowd of people.",
				"d": "        Crucified thieves."
			},
			"section": "",
			"image": "",
			"answer": "c",
			"solution": "",
			"examtype": "wassce",
			"examyear": "2013"
		},
		{
			"id": 986,
			"question": "The primary motive for Christian giving is to",
			"option": {
				"a": "go to heaven when they die",
				"b": "reciprocate God’s blessing.",
				"c": "support the work of the church.",
				"d": "provide for the servants of God"
			},
			"section": "",
			"image": "",
			"answer": "b",
			"solution": "",
			"examtype": "wassce",
			"examyear": "2011"
		},
		{
			"id": 396,
			"question": "Paul, unhappy with high incidence of idleness among the Thessalonians, commanded them to",
			"option": {
				"a": "assist those brothers who live in Idleness",
				"b": "exhort the busy-bodies to leave the church",
				"c": "ensure that any one who does not work must not eat",
				"d": "regard the lazy ones as enemies"
			},
			"section": "",
			"image": "",
			"answer": "c",
			"solution": "",
			"examtype": "wassce",
			"examyear": "2008"
		},
		{
			"id": 112,
			"question": "Jesus taught that one should make friends quickly with one’s ",
			"option": {
				"a": "enemy ",
				"b": "neighbor ",
				"c": "master ",
				"d": "accuser"
			},
			"section": "",
			"image": "",
			"answer": "d",
			"solution": "",
			"examtype": "post-utme",
			"examyear": "2010"
		},
		{
			"id": 191,
			"question": "Who was the prophet who said “I will put my law within them, and will write it upon their heart….”?  ",
			"option": {
				"a": "Isaiah  ",
				"b": "Jeremiah",
				"c": "Hosea   ",
				"d": "Amos"
			},
			"section": "",
			"image": "",
			"answer": "b",
			"solution": "",
			"examtype": "post-utme",
			"examyear": "2013"
		},
		{
			"id": 707,
			"question": "Teacher, what shall I do to inherit eternal life?” Who among the following tested Jesus with this question?",
			"option": {
				"a": "A Pharisee",
				"b": "A lawyer",
				"c": "A zealot",
				"d": "A Sadducee"
			},
			"section": "",
			"image": "",
			"answer": " b",
			"solution": "",
			"examtype": "utme",
			"examyear": "2019"
		},
		{
			"id": 992,
			"question": "Moses was bom at a period when the Hebrews were",
			"option": {
				"a": "suffering.   ",
				"b": ".   increasing",
				"c": "backsliding",
				"d": "rejoicing."
			},
			"section": "",
			"image": "",
			"answer": "a",
			"solution": "",
			"examtype": "wassce",
			"examyear": "2011"
		},
		{
			"id": 179,
			"question": "Who among the seven deacons was an evangelist  who had four daughters who prophesied?  ",
			"option": {
				"a": "Stephen  ",
				"b": "Philip   ",
				"c": "Barnabas   ",
				"d": "Nicholas"
			},
			"section": "",
			"image": "",
			"answer": "b",
			"solution": "",
			"examtype": "post-utme",
			"examyear": "2013"
		},
		{
			"id": 851,
			"question": "Which of the following people destroyed Shiloh and captured the Ark? The",
			"option": {
				"a": "Ammonites",
				"b": "Amalekites",
				"c": "Palestinians",
				"d": "Philistines"
			},
			"section": "",
			"image": "",
			"answer": "d",
			"solution": "",
			"examtype": "wassce",
			"examyear": "2012"
		},
		{
			"id": 471,
			"question": "Jesus ordered the seventy disciples not to salute any one because",
			"option": {
				"a": "their mission required urgency.",
				"b": "it is not part of their mission to salute people.",
				"c": "they may forget their mission.",
				"d": "salutations to strangers defile the Jews."
			},
			"section": "",
			"image": "",
			"answer": "a",
			"solution": "",
			"examtype": "wassce",
			"examyear": "2009"
		},
		{
			"id": 620,
			"question": "According to Isaiah, God sent him to",
			"option": {
				"a": "proclaim liberty to the captives",
				"b": "proclaim victory over Israel’s enemies",
				"c": "be a watchman over Israel",
				"d": "destroy and overthrow nations."
			},
			"section": "",
			"image": "",
			"answer": "a",
			"solution": "",
			"examtype": "utme",
			"examyear": "2010"
		},
		{
			"id": 341,
			"question": "In Corinthians, Paul stated that by one Spirit we were",
			"option": {
				"a": "free from bondage of sin",
				"b": "united into one church",
				"c": "committee to Christian service",
				"d": "baptized into one body"
			},
			"section": "",
			"image": "",
			"answer": "d",
			"solution": "",
			"examtype": "utme",
			"examyear": "2011"
		},
		{
			"id": 1045,
			"question": "Jacob’s special robe for Joseph portrayed him as a",
			"option": {
				"a": "Prince    ",
				"b": "heir     ",
				"c": "prophet     ",
				"d": "Pries"
			},
			"section": "",
			"image": "",
			"answer": "b",
			"solution": "",
			"examtype": "wassce",
			"examyear": "2015"
		},
		{
			"id": 946,
			"question": "When the people of Israel received the minority report from the spies, they decided to",
			"option": {
				"a": "kill Moses for taking them out ress at Sheehem was of Egypt to ",
				"b": "go back to Egypt. ",
				"c": "choose Caleb as their new leader",
				"d": "stone the two spies to death."
			},
			"section": "",
			"image": "",
			"answer": "b",
			"solution": "",
			"examtype": "wassce",
			"examyear": "2011"
		},
		{
			"id": 176,
			"question": "One of the following was not among the religious sects in the New Testament  ",
			"option": {
				"a": "The Pharisees   ",
				"b": "The Nazarenes",
				"c": "The Essenes",
				"d": "The Sadducees"
			},
			"section": "",
			"image": "",
			"answer": "c",
			"solution": "",
			"examtype": "post-utme",
			"examyear": "2013"
		},
		{
			"id": 212,
			"question": "Jonah typified Jesus Christ when he",
			"option": {
				"a": "surrendered himself to be swallowed by the fish",
				"b": "offered to lose his life that others might be saved",
				"c": "rejected the message of God",
				"d": "announced destruction for the Ninevites"
			},
			"section": "",
			"image": "",
			"answer": "b",
			"solution": "",
			"examtype": "wassce",
			"examyear": "2005"
		},
		{
			"id": 1079,
			"question": "The boldness of Peter and John before the Sanhedrin was attributed to",
			"option": {
				"a": "their having great influence ",
				"b": "possession of great strength ",
				"c": "their being with Jesus ",
				"d": "their ability to defend themselves"
			},
			"section": "",
			"image": "",
			"answer": "c",
			"solution": "",
			"examtype": "wassce",
			"examyear": "2015"
		},
		{
			"id": 1041,
			"question": "On the fourth day, God created the sun, moon and stars for the following purposes except. ",
			"option": {
				"a": "to separate the day from the night. ",
				"b": "for signs of seasons, days and years. ",
				"c": "to give light upon the earth. ",
				"d": "to dry up flood from the face of the earth"
			},
			"section": "",
			"image": "",
			"answer": "b",
			"solution": "",
			"examtype": "wassce",
			"examyear": "2015"
		},
		{
			"id": 1061,
			"question": "Nebuchadnezzar allowed the Chaldeans, Syrians and Moabites to attack Judah so that Judah might ",
			"option": {
				"a": "learn a lesson    ",
				"b": "be destroyed   ",
				"c": "face famine ",
				"d": "           ransack the temple"
			},
			"section": "",
			"image": "",
			"answer": "b",
			"solution": "",
			"examtype": "wassce",
			"examyear": "2015"
		},
		{
			"id": 72,
			"question": "Who baptized the Ethiopian Eunuch? ",
			"option": {
				"a": "Paul ",
				"b": "Peter ",
				"c": "Philip ",
				"d": "Rufus"
			},
			"section": "",
			"image": "",
			"answer": "c",
			"solution": "",
			"examtype": "post-utme",
			"examyear": "2008"
		},
		{
			"id": 445,
			"question": "“As each has received a gift, employ it for one another, as good stewards of God’s varied grace...” In the statement above, Peter teaches believers in virtue of",
			"option": {
				"a": "hospitality",
				"b": "giving",
				"c": "communion",
				"d": "fellowship."
			},
			"section": "",
			"image": "",
			"answer": "a",
			"solution": "",
			"examtype": "utme",
			"examyear": "2013"
		},
		{
			"id": 502,
			"question": "Before Moses brought the Israelites to meet God on Mount Sinai, he charged them to",
			"option": {
				"a": "touch the mountain at the sight of smoke",
				"b": "ensure they eat very well",
				"c": "wash the garments and be consecrated",
				"d": "mate with their wives for three days"
			},
			"section": "",
			"image": "",
			"answer": "c",
			"solution": "",
			"examtype": "utme",
			"examyear": "2015"
		},
		{
			"id": 229,
			"question": "One of the early Christians who sold his property and gave the money to the apostles was",
			"option": {
				"a": "Barnabas",
				"b": "Stephen",
				"c": "Barabbas",
				"d": "Matthias"
			},
			"section": "",
			"image": "",
			"answer": "a",
			"solution": "",
			"examtype": "wassce",
			"examyear": "2005"
		}
	]
}
